scprotein/__init__.py
scprotein/model.py
scprotein/prototype_loss.py
scprotein/utils.py
scprotein/peptide_uncertainty_estimation/__init__.py
scprotein/peptide_uncertainty_estimation/multi_task_heteroscedastic_regression_loss.py
scprotein/peptide_uncertainty_estimation/multi_task_heteroscedastic_regression_model.py
scprotein/peptide_uncertainty_estimation/peptide_uncertainty_utils.py
scprotein-1.1.1.dist-info/LICENSE
scprotein-1.1.1.dist-info/METADATA
scprotein-1.1.1.dist-info/WHEEL
scprotein-1.1.1.dist-info/top_level.txt
scprotein-1.1.1.dist-info/RECORD
