Metadata-Version: 2.1
Name: scprotein
Version: 1.1.1
Summary: scprotein is a deep contrastive learning framework for single-cell proteomics embedding.
Home-page: https://github.com/TencentAILabHealthcare/scPROTEIN
Author: LiWei
Author-email: nkuweili@mail.nankai.edu.cn
License: Apache
Platform: UNKNOWN
Requires-Python: >=3.8
Requires-Dist: torch (>=1.10.0)
Requires-Dist: scanpy (>=1.8.2)
Requires-Dist: numpy (>=1.22.3)
Requires-Dist: pandas (>=1.3.5)
Requires-Dist: scipy (>=1.8.1)
Requires-Dist: scikit-learn (>=1.1.1)
Requires-Dist: torch-geometric (>=2.0.4)
